CureQ/__init__.py
CureQ/__main__.py
CureQ/mea.py
CureQ/GUI/MEAlytics_logo.ico
CureQ/GUI/__init__.py
CureQ/GUI/_batch_processing.py
CureQ/GUI/_compress_files.py
CureQ/GUI/_exclude_electrodes.py
CureQ/GUI/_heatmap.py
CureQ/GUI/_parameters.py
CureQ/GUI/_plotting.py
CureQ/GUI/_process_file.py
CureQ/GUI/_single_electrode_view.py
CureQ/GUI/_view_results.py
CureQ/GUI/_whole_well_view.py
CureQ/GUI/mea_analysis_tool.py
CureQ/GUI/theme.json
CureQ/core/__init__.py
CureQ/core/_bandpass.py
CureQ/core/_burst_detection.py
CureQ/core/_features.py
CureQ/core/_heatmap.py
CureQ/core/_heatmap_old.py
CureQ/core/_network_burst_detection.py
CureQ/core/_plotting.py
CureQ/core/_spike_validation.py
CureQ/core/_threshold.py
CureQ/core/_utilities.py
CureQ/core/adjust_h5_size.py
CureQ/ipywidgets_ui/__init__.py
CureQ/ipywidgets_ui/app.py
CureQ/ipywidgets_ui/pages/__init__.py
cureq-1.2.18.dist-info/LICENSE
cureq-1.2.18.dist-info/METADATA
cureq-1.2.18.dist-info/WHEEL
cureq-1.2.18.dist-info/entry_points.txt
cureq-1.2.18.dist-info/top_level.txt
cureq-1.2.18.dist-info/RECORD
