Metadata-Version: 2.1
Name: cureq
Version: 1.2.18
Summary: Library for analyzing MEA files.
Home-page: https://github.com/CureQ/CureQ.git
Author: CureQ
Author-email: cureq-ft@hva.nl
Classifier: Programming Language :: Python :: 3
Classifier: License :: OSI Approved :: GNU General Public License v3 or later (GPLv3+)
Classifier: Operating System :: OS Independent
License-File: LICENSE
Requires-Dist: matplotlib >=3.7.3
Requires-Dist: numpy >=1.26.4
Requires-Dist: h5py >=3.9.0
Requires-Dist: pandas >=2.1.4
Requires-Dist: scipy >=1.11.4
Requires-Dist: seaborn >=0.12.2
Requires-Dist: statsmodels >=0.14.0
Requires-Dist: scikit-image >=0.22.0
Requires-Dist: KDEpy >=1.1.9
Requires-Dist: customtkinter >=5.2.2
Requires-Dist: CTkToolTip >=0.8
Requires-Dist: CTkMessagebox >=2.7
Requires-Dist: CTkColorPicker >=0.9.0
Requires-Dist: requests >=2.32.3
Requires-Dist: pyshortcuts >=1.9.5
Provides-Extra: widgets
Requires-Dist: ipywidgets >=8.1.2 ; extra == 'widgets'
Requires-Dist: voila >=0.5.6 ; extra == 'widgets'
Requires-Dist: plotly >=5.16.1 ; extra == 'widgets'
